pyspark_graph/__init__.py
pyspark_graph/datalog.py
pyspark_graph/graph.py
pyspark_graph/util.py
pyspark_graph/algorithms/__init__.py
pyspark_graph/algorithms/aggregate_messages.py
pyspark_graph/algorithms/bfs.py
pyspark_graph/algorithms/connected_components.py
pyspark_graph/algorithms/jaccard_similarity.py
pyspark_graph/algorithms/katz_index.py
pyspark_graph/algorithms/label_propagation.py
pyspark_graph/algorithms/overlap_coefficient.py
pyspark_graph/algorithms/pregel.py
pyspark_graph/algorithms/shortest_paths.py
pyspark_graph/algorithms/triangle_count.py
pyspark_graph/algorithms/wl_kernel.py
pyspark_graph-0.0.9.dist-info/LICENSE
pyspark_graph-0.0.9.dist-info/METADATA
pyspark_graph-0.0.9.dist-info/WHEEL
pyspark_graph-0.0.9.dist-info/top_level.txt
pyspark_graph-0.0.9.dist-info/RECORD
