Metadata-Version: 2.1
Name: pyspark-graph
Version: 0.0.9
Summary: Pure pyspark implementation of graph algorithms
Author-email: Joshua <author@example.com>
Project-URL: Homepage, https://github.com/aktungmak/pyspark-graph
Project-URL: Issues, https://github.com/aktungmak/pyspark-graph/issues
Keywords: spark,pyspark,graph,graphx,graphframes
Classifier: Programming Language :: Python :: 3
Classifier: License :: OSI Approved :: Apache Software License
Classifier: Operating System :: OS Independent
Classifier: Development Status :: 4 - Beta
Requires-Python: >=3.10
License-File: LICENSE
Requires-Dist: pyspark >=3.5
